cattle_hugs/__init__.py
cattle_hugs/types.py
cattle_hugs/version.py
cattle_hugs/database/__init__.py
cattle_hugs/database/models.py
cattle_hugs/database/object_models.py
cattle_hugs/processing/__init__.py
cattle_hugs/processing/for_actor.py
cattle_hugs/processing/objects.py
cattle_hugs/processing/test_for_actor.py
cattle_hugs/processing/test_objects.py
cattle_hugs/processing/test_objects_broker.py
cattle_hugs/processing/test_trees.py
cattle_hugs/processing/testing.py
cattle_hugs/processing/trees.py
cattle_hugs/public/__init__.py
cattle_hugs/public/interactions.py
cattle_hugs/public/objects.py
cattle_hugs/public/objects_server.py
cattle_hugs/public/test_actor.py
cattle_hugs/public/test_interactions.py
cattle_hugs/public/test_objects.py
cattle_hugs/testing/__init__.py
cattle_hugs/testing/app.py
cattle_hugs/testing/fixtures.py
cattle_hugs-0.1.1.dist-info/METADATA
cattle_hugs-0.1.1.dist-info/WHEEL
cattle_hugs-0.1.1.dist-info/RECORD
