Metadata-Version: 2.4
Name: cattle-hugs
Version: 0.1.1
Project-URL: Repository, https://codeberg.org/bovine/cattle_hugs
Requires-Python: >=3.11
Requires-Dist: cattle-grid>=0.5.18
Requires-Dist: muck-out>=0.3.15
